test_package/__init__.py
test_package/info1.py
test_package/main.py
test_package/operator1.py
test_package/push_to_baidu.py
test_package/test.py
test_package/test_package2/__init__.py
test_package/test_package2/info2.py
test_package/test_package2/operator2.py
lwg_jack_project_demo-1.0.1.dist-info/LICENSE
lwg_jack_project_demo-1.0.1.dist-info/METADATA
lwg_jack_project_demo-1.0.1.dist-info/WHEEL
lwg_jack_project_demo-1.0.1.dist-info/top_level.txt
lwg_jack_project_demo-1.0.1.dist-info/RECORD
