Metadata-Version: 2.1
Name: lwg-jack-project-demo
Version: 1.0.1
Summary: test Python packaging
Home-page: https://www.baidu.com/
Author: jacky
Author-email: jacky@g.com
Requires-Python: >=3.6
License-File: LICENSE
Requires-Dist: requests
